HDL/mem.vhd
library ieee;
use ieee.std_logic_1164.all;
use ieee.numeric_std.all;

entity mem is
    port(
        clk :in std_logic;
        ld :in std_logic;
        oe :in std_logic;
        addr_in :in std_logic_vector(3 downto 0);
        data_in :in std_logic_vector(7 downto 0);
        data_out :out std_logic_vector(7 downto 0)
    );
end entity;

architecture behave of mem is
type mem_type is array (0 to 15) of std_logic_vector(7 downto 0);
signal mem_obj : mem_type;
    begin
        process(clk)
        begin
            if rising_edge(clk) then
                if ld='1' then
                    mem_obj(to_integer(unsigned(addr_in)))<=data_in;
                end if;
                if oe='1' then
                    data_out<=mem_obj(to_integer(unsigned(addr_in)));
                end if;
            end if;
        end process;
end behave;

HDL/mar.vhd
library ieee;
use ieee.std_logic_1164.all;
use ieee.numeric_std.all;

entity mar is
    port(
        clk : in std_logic;
        rst : in std_logic;
        ld : in std_logic;
        inputs : in std_logic_vector (3 downto 0);
        outputs : out std_logic_vector (3 downto 0)
    );
end entity;

architecture behave of mar is
signal stored_value : std_logic_vector (3 downto 0):=(others => 'Z');
begin
    process(clk,rst)
    begin
        if rst ='1' then
            stored_value <=(others=>'Z');
        elsif rising_edge(clk) then
            if ld='1' then
                stored_value<=inputs;
            end if;
        end if;

    end process;
outputs <= stored_value;

end behave;

Testbench/mem_mar_init_tb.vhd
library ieee;
use ieee.std_logic_1164.all;
use ieee.numeric_std.all;

entity mem_mar_init_tb is 
    
end entity;

architecture behave of mem_mar_init_tb is
    component mar is
        port (
            clk : in std_logic;
            rst : in std_logic;
            ld : in std_logic;
            inputs : in std_logic_vector (3 downto 0);
            outputs : out std_logic_vector (3 downto 0)
        );
    end component;

    component mem is
        port(
        clk :in std_logic;
        ld :in std_logic;
        oe :in std_logic;
        addr_in :in std_logic_vector(3 downto 0);
        data_in :in std_logic_vector(7 downto 0);
        data_out :out std_logic_vector(7 downto 0)
    );
    end component;

    signal clk_sig :  std_logic;
    signal rst_sig :  std_logic;
    signal ld_sig :  std_logic;
    signal inputs_sig : std_logic_vector (3 downto 0);
    signal outputs_sig : std_logic_vector (3 downto 0); 


    signal oe_sig_mem :  std_logic;
    signal ld_sig_mem :  std_logic;
    signal addr_in_sig_mem : std_logic_vector (3 downto 0);
    signal data_out_sig_mem : std_logic_vector (7 downto 0); 
    signal data_in_sig_mem : std_logic_vector (7 downto 0); 

    constant clk_period : time := 10 ns;
begin
    mar1 : mar port map (clk=>clk_sig, rst =>rst_sig, ld=> ld_sig, inputs=> inputs_sig, outputs=>outputs_sig); 
    mem1 : mem port map (clk=>clk_sig,ld=>ld_sig_mem,oe=>oe_sig_mem,addr_in=>addr_in_sig_mem, data_in=>data_in_sig_mem,data_out=>data_out_sig_mem);   
    process
       begin
        clk_sig<='0';
        wait for clk_period/2;
        clk_sig<=not clk_sig;
        wait for clk_period/2;
    end process;

    process
    begin
        --rst_sig<='0';
        --inputs_sig <="0001";
        --ld_sig<='1';
        --wait for clk_period*5;
        --ld_sig<='0';
        --data_in_sig_mem<="11111111";
        --ld_sig_mem<='1';
        --wait for clk_period;
        --ld_sig_mem<='0';
        --wait for clk_period;
        --oe_sig_mem<='1';
        --wait for clk_period;
        inputs_sig<="0000";
        ld_sig<='1';
        wait for clk_period;
        ld_sig<='0';
        oe_sig_mem<='1';
        wait for clk_period;
        inputs_sig<="0001";
        ld_sig<='1';
        wait for clk_period;
        ld_sig<='0';
        oe_sig_mem<='1';
        wait for clk_period;
        inputs_sig<="0010";
        ld_sig<='1';
        wait for clk_period;
        ld_sig<='0';
        wait;
    end process;
end behave;

Testbench/waveform_mem_init.vcd
$date
  Tue Jan 21 18:23:38 2025
$end
$version
  GHDL v0
$end
$timescale
  1 fs
$end
$scope module standard $end
$upscope $end
$scope module std_logic_1164 $end
$upscope $end
$scope module numeric_std $end
$upscope $end
$scope module textio $end
$upscope $end
$scope module std_logic_textio $end
$upscope $end
$scope module mem_mar_init_tb $end
$var reg 1 ! clk_sig $end
$var reg 1 " rst_sig $end
$var reg 1 # ld_sig $end
$var reg 4 $ inputs_sig[3:0] $end
$var reg 4 % outputs_sig[3:0] $end
$var reg 1 & oe_sig_mem $end
$var reg 1 ' ld_sig_mem $end
$var reg 4 ( addr_in_sig_mem[3:0] $end
$var reg 8 ) data_out_sig_mem[7:0] $end
$var reg 8 * data_in_sig_mem[7:0] $end
$scope module mar1 $end
$var reg 1 + clk $end
$var reg 1 , rst $end
$var reg 1 - ld $end
$var reg 4 . inputs[3:0] $end
$var reg 4 / outputs[3:0] $end
$var reg 4 0 stored_value[3:0] $end
$upscope $end
$scope module mem1 $end
$var reg 1 1 clk $end
$var reg 1 2 ld $end
$var reg 1 3 oe $end
$var reg 4 4 addr_in[3:0] $end
$var reg 8 5 data_in[7:0] $end
$var reg 8 6 data_out[7:0] $end
$comment mem_obj is not handled $end
$upscope $end
$upscope $end
$enddefinitions $end
#0
0!
U"
1#
b0000 $
bZZZZ %
U&
U'
bUUUU (
bUUUUUUUU )
bUUUUUUUU *
0+
U,
1-
b0000 .
bZZZZ /
bZZZZ 0
01
U2
U3
bUUUU 4
bUUUUUUUU 5
bUUUUUUUU 6
#5000000
1!
b0000 %
1+
b0000 /
b0000 0
11
#10000000
0!
0#
1&
0+
0-
01
13
#15000000
1!
1+
11
#20000000
0!
1#
b0001 $
0+
1-
b0001 .
01
#25000000
1!
b0001 %
1+
b0001 /
b0001 0
11
#30000000
0!
0#
0+
0-
01
#35000000
1!
1+
11
#40000000
0!
1#
b0010 $
0+
1-
b0010 .
01
#45000000
1!
b0010 %
1+
b0010 /
b0010 0
11
#50000000
0!
0#
0+
0-
01
