HDL/alu.vhd
library ieee;
use ieee.std_logic_1164.all;
use ieee.numeric_std.all;

entity alu is
    port(
        en : in std_logic;
        op : in std_logic;
        reg_a_in : in std_logic_vector ( 7 downto 0);
        reg_b_in : in std_logic_vector ( 7 downto 0);
        carry_out : out std_logic;
        zero_flag : out std_logic;
        res_out : out std_logic_vector ( 7 downto 0)
    );
end entity;

architecture behave of alu is
    signal result : std_logic_vector ( 8 downto 0);
    begin
        process (op, reg_a_in, reg_b_in,en )
        begin
                if op='0' then
                    result <= std_logic_vector(resize(unsigned(reg_a_in), 9) + resize(unsigned(reg_b_in), 9));
                elsif op='1' then
                    result <= std_logic_vector(resize(unsigned(reg_a_in), 9) - resize(unsigned(reg_b_in), 9));
                end if;
        
        end process;
carry_out <= result(8) when en='1' else 'Z';
zero_flag <= '1' when result(7 downto 0) = "00000000" else '0';
res_out <= result(7 downto 0) when en='1' else (others =>'Z');
end behave;

HDL/gen_reg.vhd
library ieee;
use ieee.std_logic_1164.all;
use ieee.numeric_std.all;

entity gen_reg is
    port(
        clk : in std_logic;
        rst : in std_logic;
        out_en : in std_logic;
        ld : in std_logic;
        inputs : in std_logic_vector (7 downto 0);
        outputs : out std_logic_vector (7 downto 0);
        outputs_alu : out std_logic_vector (7 downto 0)
    );
end entity;

architecture behave of gen_reg is
signal stored_value : std_logic_vector (7 downto 0):=(others => 'Z');
begin
    process(clk,rst)
    begin
        if rst ='1' then
            stored_value <=(others=>'Z');
        elsif rising_edge(clk) then
            if ld='1' then
                stored_value<=inputs;
            end if;
        end if;

    end process;
outputs <= stored_value when out_en ='1' else (others => 'Z');
outputs_alu <= stored_value;

end behave;

HDL/mem.vhd
library ieee;
use ieee.std_logic_1164.all;
use ieee.numeric_std.all;
use ieee.std_logic_textio.all;

library std;
use std.textio.all;

entity mem is
    port(
        clk :in std_logic;
        ld :in std_logic;
        oe :in std_logic;
        addr_in :in std_logic_vector(3 downto 0);
        data_in :in std_logic_vector(7 downto 0);
        data_out :out std_logic_vector(7 downto 0)
    );
end entity;

architecture behave of mem is
type mem_type is array (0 to 15) of std_logic_vector(7 downto 0);


--function init(file_name:string) return mem_type is
--       file file_data : text;
--        variable fstatus : file_open_status;
--        variable text_line : line;
--       variable line_content : std_logic_vector (7 downto 0);
--       variable i : integer :=0;
--        variable mem_temp : mem_type;
--    begin
--           file_open(fstatus,file_data,file_name,READ_MODE);
--            if fstatus=open_ok then
--                while(i<16) loop
--                    readLine(file_data,text_line);
--                    read(text_line,line_content);
--                    mem_temp(i):=line_content;
--                    i:=i+1;
--                end loop;
--                file_close(file_data); 
--                else
--                    report "Failed to open file: " & file_name severity error;
--                end if;
--        return mem_temp;


--end function init;
signal mem_obj : mem_type:=(x"0E",x"2F",x"1E",x"5E",x"41",x"00",x"00",x"00",x"00",x"00",x"00",x"00",x"00",x"00",x"00",x"01");
    begin
        process(clk)
        begin
            if rising_edge(clk) then
                if ld='1' then
                    mem_obj(to_integer(unsigned(addr_in)))<=data_in;
                end if;
                if oe='1' then
                    data_out<=mem_obj(to_integer(unsigned(addr_in)));
                else
                    data_out<="ZZZZZZZZ";
                end if;
            end if;
        end process;
end behave;

HDL/mar.vhd
library ieee;
use ieee.std_logic_1164.all;
use ieee.numeric_std.all;

entity mar is
    port(
        clk : in std_logic;
        rst : in std_logic;
        ld : in std_logic;
        inputs : in std_logic_vector (3 downto 0);
        outputs : out std_logic_vector (3 downto 0)
    );
end entity;

architecture behave of mar is
signal stored_value : std_logic_vector (3 downto 0):=(others => 'Z');
begin
    process(clk,rst)
    begin
        if rst ='1' then
            stored_value <=(others=>'Z');
        elsif rising_edge(clk) then
            if ld='1' then
                stored_value<=inputs;
            end if;
        end if;

    end process;
outputs <= stored_value;

end behave;

HDL/cu.vhd
library ieee;
use ieee.std_logic_1164.all;
use ieee.numeric_std.all;

entity cu is 
port(
    clk: in std_logic;
    rst:in std_logic;
    inst:in std_logic_vector(3 downto 0);
    do: out std_logic_vector(16 downto 0)
);
end entity;

architecture behave of cu is
signal count : unsigned(3 downto 0) := "0000";
    begin
        count_proc:process(clk,rst)
        begin
            if rst='1' then
                count<="0000";
            elsif rising_edge(clk) then
                if count="1010" then
                    count<="0000";
                else
                    count<=count+1;
                end if;
            end if;
        end process;

        --coding of the do
        --HLT--OUT_IN--OUT_OUT--ALU_OP_EN--ALU_EN--PC_EN--PC_IN--PC_OUT-MAR_IN--RAM_IN--RAM_OUT--A_IN--A_OUT--B_IN--B_OUT--INST_I--INST_OUT
        --16 --15 -----14--------13--------12------11------10-----9-----8---------7-------6-------5-----4------3------2------1--------0
        do <= "00000001100000000" when count = "0000" else --load memory
      "00000100001000010" when count = "0001" else --increment pc 
      
      
      --LDA
      "00000000000000001" when (count = "0010" and inst="0000") else --inst out from ir to mar
      "00000000100000001" when (count = "0011" and inst="0000") else --mar_in to mem
      "00000000001100000" when (count = "0100" and inst="0000") else --from mem to reg A
      "00000000000000000" when (count = "0101" and inst="0000") else --nothing here
      "00000000000000000" when (count = "0110" and inst="0000") else --nothing here
      
      "00000000000000001" when (count= "0010" and inst="0001") else	--INST_REG-> main_bus
      "00000000100000001" when (count= "0011" and inst="0001") else
      "00000000010010000" when (count= "0100" and inst="0001") else    
      "00000000000000000" when (count= "0101" and inst="0001") else    
      "00000000000000000" when (count= "0110" and inst="0001") else
       
      --ADD
      "00000000000000001" when (count= "0010" and inst="0010") else    
      "00000000100000001" when (count= "0011" and inst="0010") else
      "00000000001001000" when (count= "0100" and inst="0010") else    
      "00001000000000000" when (count= "0101" and inst="0010") else    
      "00001000000100000" when (count= "0110" and inst="0010") else
       
      --SUB
      "00000000000000001" when (count= "0010" and inst="0011") else    
      "00000000100000001" when (count= "0011" and inst="0011") else
      "00000000001001000" when (count= "0100" and inst="0011") else    
      "00010000000000000" when (count= "0101" and inst="0011") else    
      "00011000000100000" when (count= "0110" and inst="0011") else
       
      --JMP
      "00000000000000001" when (count= "0010" and inst="0100") else    
      "00000010000000001" when (count= "0011" and inst="0100") else
      "00000000000000000" when (count= "0100" and inst="0100") else    
      "00000000000000000" when (count= "0101" and inst="0100") else    
      "00000000000000000" when (count= "0110" and inst="0100") else
      
      --OUT
      "00000000000000001" when (count= "0010" and inst="0101") else    
      "00000000100000001" when (count= "0011" and inst="0101") else
      "00000000001000000" when (count= "0100" and inst="0101") else
      "01000000001000000" when (count= "0101" and inst="0101") else
      "00100000000000000" when (count= "0110" and inst="0101") else
      
      --HLT
      "10000000000000000" when (count= "0010" and inst="0110") else    
      "10000010000000000" when (count= "0011" and inst="0110") else
      "00000000000000000" when (count= "0100" and inst="0110") else    
      "00000000000000000" when (count= "0101" and inst="0110") else    
      "00000000000000000" when (count= "0110" and inst="0110") ;
end behave;

HDL/pc.vhd
library ieee;
use ieee.std_logic_1164.all;
use ieee.numeric_std.all;

entity pc is 
    port(
        clk : in std_logic;
        rst : in std_logic;
        en : in std_logic;
        oe : in std_logic;
        ld : in std_logic;
        inputs : in std_logic_vector(3 downto 0);
        outputs : out std_logic_vector (3 downto 0)
    );
end entity;

architecture behave of pc is
    signal count : unsigned(3 downto 0) := "0000";
    begin
    process(clk,rst)
        begin
        if rst ='1' then
            count <=(others=>'0');
        elsif
            rising_edge(clk) then
                if ld='1'  then
                    count <= unsigned(inputs); 
                elsif en='1' then
                    count <= count + 1;
                end if;
        end if;
    end process;
    outputs <= std_logic_vector(count) when oe ='1' else "ZZZZ";
end behave;

HDL/cpu.vhd
library ieee;
use ieee.std_logic_1164.all;
use ieee.numeric_std.all;

entity cpu is 
port(
    clk: in std_logic;
    rst:in std_logic;
    op: out std_logic_vector(7 downto 0)
);
end entity;

architecture behave of cpu is
    component alu is
        port(
        en : in std_logic;
        op : in std_logic;
        reg_a_in : in std_logic_vector ( 7 downto 0);
        reg_b_in : in std_logic_vector ( 7 downto 0);
        carry_out : out std_logic;
        zero_flag : out std_logic;
        res_out : out std_logic_vector ( 7 downto 0)
    );
    end component;
    component cu is
        port(
        clk: in std_logic;
        rst:in std_logic;
        inst:in std_logic_vector(3 downto 0);
        do: out std_logic_vector(16 downto 0)
    );
    end component;
    component gen_reg is
        port(
        clk : in std_logic;
        rst : in std_logic;
        out_en : in std_logic;
        ld : in std_logic;
        inputs : in std_logic_vector (7 downto 0);
        outputs : out std_logic_vector (7 downto 0);
        outputs_alu : out std_logic_vector (7 downto 0)
    );
    end component;
    component mar is
        port(
        clk : in std_logic;
        rst : in std_logic;
        ld : in std_logic;
        inputs : in std_logic_vector (3 downto 0);
        outputs : out std_logic_vector (3 downto 0)
    );
    end component;
    component mem is
        port(
        clk :in std_logic;
        ld :in std_logic;
        oe :in std_logic;
        addr_in :in std_logic_vector(3 downto 0);
        data_in :in std_logic_vector(7 downto 0);
        data_out :out std_logic_vector(7 downto 0)
    );
    end component;
    component pc is
        port(
        clk : in std_logic;
        rst : in std_logic;
        en : in std_logic;
        oe : in std_logic;
        ld : in std_logic;
        inputs : in std_logic_vector(3 downto 0);
        outputs : out std_logic_vector (3 downto 0)
    );
    end component;

     signal clk_sig : std_logic;
     signal halt_sig : std_logic;

     --ALU
        
    --CU
signal main_bus : std_logic_vector (7 downto 0);      
signal  pc_en_sig : std_logic;
signal  pc_oe_sig : std_logic;
signal  pc_ld_sig : std_logic;

signal inst_out : std_logic_vector (3 downto 0);
signal inst_out_sig : std_logic_vector (7 downto 0);
signal mar_mem_sig : std_logic_vector (3 downto 0);


signal cu_out_sig : std_logic_vector (16 downto 0);
signal mar_ld_sig : std_logic;
signal mem_oe_sig : std_logic;
signal mem_ld_sig : std_logic;
signal inst_ld_sig : std_logic;
signal inst_oe_sig : std_logic;

signal reg_op_oe_sig : std_logic;
signal reg_op_ld_sig : std_logic;
signal reg_a_oe_sig : std_logic;
signal reg_a_ld_sig : std_logic;
signal reg_b_oe_sig : std_logic;
signal reg_b_ld_sig : std_logic;
signal reg_b_alu : std_logic_vector (7 downto 0);
signal reg_a_alu : std_logic_vector (7 downto 0);

signal alu_en_sig : std_logic;
signal alu_op_sig : std_logic;




begin
    clk_sig <= clk and (not halt_sig);

    pc_inst : pc port map (
        clk =>clk_sig, 
        rst=>rst, 
        en => pc_en_sig,
        oe => pc_oe_sig,
        ld => pc_ld_sig, 
        inputs => main_bus(3 downto 0), 
        outputs =>main_bus(3 downto 0)
        );

    cu_inst : cu port map (
        clk=>clk_sig ,
        rst=> rst, 
        inst=> inst_out,
        do => cu_out_sig
    );
    mar_inst : mar port map (
        clk => clk_sig,
        rst => rst,
        ld => mar_ld_sig,
        inputs => main_bus(3 downto 0),
        outputs => mar_mem_sig
    );
    mem_inst : mem port map (
        clk => clk_sig,
        ld => mem_ld_sig,
        oe => mem_oe_sig,
        addr_in => mar_mem_sig,
        data_in => main_bus,
        data_out => main_bus
    );
    inst_reg_inst : gen_reg port map (
        clk => clk_sig,
        rst => rst,
        out_en => inst_oe_sig,
        ld => inst_ld_sig,
        inputs => main_bus,
        outputs_alu=> inst_out_sig
    );

    inst_out<=inst_out_sig(7 downto 4);
    main_bus(3 downto 0)<=inst_out_sig (3 downto 0) when inst_oe_sig='1' else (others=>'Z');

    reg_A_inst : gen_reg port map (
        clk => clk_sig,
        rst => rst,
        out_en => reg_a_oe_sig,
        ld => reg_a_ld_sig,
        inputs => main_bus,
        outputs => main_bus,
        outputs_alu=> reg_a_alu
    );
    reg_B_inst : gen_reg port map (
        clk => clk_sig,
        rst => rst,
        out_en => reg_a_oe_sig,
        ld => reg_b_ld_sig,
        inputs => main_bus,
        outputs => main_bus,
        outputs_alu=> reg_b_alu
    );
    reg_op_inst : gen_reg port map (
        clk => clk_sig,
        rst => rst,
        out_en => reg_op_oe_sig,
        ld => reg_op_ld_sig,
        inputs => main_bus,
        outputs => open,
        outputs_alu=> op
    );
    alu_inst : alu port map (
        en => alu_en_sig,
        op => alu_op_sig,
        reg_a_in => reg_a_alu,
        reg_b_in => reg_b_alu,
        carry_out => open,
        zero_flag => open,
        res_out => main_bus
    );
    halt_sig 	<= cu_out_sig(16);
    reg_op_ld_sig 	<=cu_out_sig(15);
    reg_op_oe_sig	<=cu_out_sig(14);
    alu_op_sig	<= cu_out_sig(13);
    alu_en_sig	<= cu_out_sig(12);
    pc_en_sig 	<= cu_out_sig(11);
    pc_ld_sig	<= cu_out_sig(10);
    pc_oe_sig 	<= cu_out_sig(9);
    mar_ld_sig 	<= cu_out_sig(8);
    mem_ld_sig	<= cu_out_sig(7);
    mem_oe_sig	<= cu_out_sig(6);
    reg_a_ld_sig<= cu_out_sig(5);
    reg_a_oe_sig<= cu_out_sig(4);
    reg_b_ld_sig<= cu_out_sig(3);
    reg_b_oe_sig<= cu_out_sig(2);
    inst_ld_sig	<= cu_out_sig(1);
    inst_oe_sig	<= cu_out_sig(0);

end behave;

Testbench/cpu_tb.vhd
library ieee;
use ieee.std_logic_1164.all;
use ieee.numeric_std.all;

entity cpu_tb is
    
end entity;

architecture behave of cpu_tb is
    component cpu is 
    port(
        clk: in std_logic;
        rst:in std_logic;
        op: out std_logic_vector(7 downto 0)
    );
    end component;
    constant clk_period : time := 50 ns;
    signal clk_sig : std_logic;
    signal nclk_sig : std_logic;
    signal rst_sig : std_logic;
    signal op_cpu_sig : std_logic_vector(7 downto 0);

    begin
        cpu1 : cpu port map (clk=>clk_sig,rst=>rst_sig, op=> op_cpu_sig);
        process
        begin
         clk_sig<='0';
         wait for clk_period/2;
         clk_sig<=not clk_sig;
         wait for clk_period/2;
     end process;
     nclk_sig <= not clk_sig;
     process

begin

wait for clk_period*14;
rst_sig<='1' ;
wait for clk_period*10;
rst_sig<='0'; 
wait;

end process;
end behave;

Testbench/waveform_cpu.vcd
$date
  Wed Jan 22 01:33:12 2025
$end
$version
  GHDL v0
$end
$timescale
  1 fs
$end
$scope module standard $end
$upscope $end
$scope module std_logic_1164 $end
$upscope $end
$scope module numeric_std $end
$upscope $end
$scope module textio $end
$upscope $end
$scope module std_logic_textio $end
$upscope $end
$scope module cpu_tb $end
$var reg 1 ! clk_sig $end
$var reg 1 " nclk_sig $end
$var reg 1 # rst_sig $end
$var reg 8 $ op_cpu_sig[7:0] $end
$scope module cpu1 $end
$var reg 1 % clk $end
$var reg 1 & rst $end
$var reg 8 ' op[7:0] $end
$var reg 1 ( clk_sig $end
$var reg 1 ) halt_sig $end
$var reg 8 * main_bus[7:0] $end
$var reg 1 + pc_en_sig $end
$var reg 1 , pc_oe_sig $end
$var reg 1 - pc_ld_sig $end
$var reg 4 . inst_out[3:0] $end
$var reg 8 / inst_out_sig[7:0] $end
$var reg 4 0 mar_mem_sig[3:0] $end
$var reg 17 1 cu_out_sig[16:0] $end
$var reg 1 2 mar_ld_sig $end
$var reg 1 3 mem_oe_sig $end
$var reg 1 4 mem_ld_sig $end
$var reg 1 5 inst_ld_sig $end
$var reg 1 6 inst_oe_sig $end
$var reg 1 7 reg_op_oe_sig $end
$var reg 1 8 reg_op_ld_sig $end
$var reg 1 9 reg_a_oe_sig $end
$var reg 1 : reg_a_ld_sig $end
$var reg 1 ; reg_b_oe_sig $end
$var reg 1 < reg_b_ld_sig $end
$var reg 8 = reg_b_alu[7:0] $end
$var reg 8 > reg_a_alu[7:0] $end
$var reg 1 ? alu_en_sig $end
$var reg 1 @ alu_op_sig $end
$scope module pc_inst $end
$var reg 1 A clk $end
$var reg 1 B rst $end
$var reg 1 C en $end
$var reg 1 D oe $end
$var reg 1 E ld $end
$var reg 4 F inputs[3:0] $end
$var reg 4 G outputs[3:0] $end
$var reg 4 H count[3:0] $end
$upscope $end
$scope module cu_inst $end
$var reg 1 I clk $end
$var reg 1 J rst $end
$var reg 4 K inst[3:0] $end
$var reg 17 L do[16:0] $end
$var reg 4 M count[3:0] $end
$upscope $end
$scope module mar_inst $end
$var reg 1 N clk $end
$var reg 1 O rst $end
$var reg 1 P ld $end
$var reg 4 Q inputs[3:0] $end
$var reg 4 R outputs[3:0] $end
$var reg 4 S stored_value[3:0] $end
$upscope $end
$scope module mem_inst $end
$var reg 1 T clk $end
$var reg 1 U ld $end
$var reg 1 V oe $end
$var reg 4 W addr_in[3:0] $end
$var reg 8 X data_in[7:0] $end
$var reg 8 Y data_out[7:0] $end
$comment mem_obj is not handled $end
$upscope $end
$scope module inst_reg_inst $end
$var reg 1 Z clk $end
$var reg 1 [ rst $end
$var reg 1 \ out_en $end
$var reg 1 ] ld $end
$var reg 8 ^ inputs[7:0] $end
$var reg 8 _ outputs[7:0] $end
$var reg 8 ` outputs_alu[7:0] $end
$var reg 8 a stored_value[7:0] $end
$upscope $end
$scope module reg_a_inst $end
$var reg 1 b clk $end
$var reg 1 c rst $end
$var reg 1 d out_en $end
$var reg 1 e ld $end
$var reg 8 f inputs[7:0] $end
$var reg 8 g outputs[7:0] $end
$var reg 8 h outputs_alu[7:0] $end
$var reg 8 i stored_value[7:0] $end
$upscope $end
$scope module reg_b_inst $end
$var reg 1 j clk $end
$var reg 1 k rst $end
$var reg 1 l out_en $end
$var reg 1 m ld $end
$var reg 8 n inputs[7:0] $end
$var reg 8 o outputs[7:0] $end
$var reg 8 p outputs_alu[7:0] $end
$var reg 8 q stored_value[7:0] $end
$upscope $end
$scope module reg_op_inst $end
$var reg 1 r clk $end
$var reg 1 s rst $end
$var reg 1 t out_en $end
$var reg 1 u ld $end
$var reg 8 v inputs[7:0] $end
$var reg 8 w outputs[7:0] $end
$var reg 8 x outputs_alu[7:0] $end
$var reg 8 y stored_value[7:0] $end
$upscope $end
$scope module alu_inst $end
$var reg 1 z en $end
$var reg 1 { op $end
$var reg 8 | reg_a_in[7:0] $end
$var reg 8 } reg_b_in[7:0] $end
$var reg 1 !" carry_out $end
$var reg 1 "" zero_flag $end
$var reg 8 #" res_out[7:0] $end
$var reg 9 $" result[8:0] $end
$upscope $end
$upscope $end
$upscope $end
$enddefinitions $end
#0
0!
1"
U#
bZZZZZZZZ $
0%
U&
bZZZZZZZZ '
0(
0)
bUUUUUUUU *
0+
1,
0-
bZZZZ .
bZZZZZZZZ /
bZZZZ 0
b00000001100000000 1
12
03
04
05
06
07
08
09
0:
0;
0<
bZZZZZZZZ =
bZZZZZZZZ >
0?
0@
0A
UB
0C
1D
0E
bUUUU F
bUUUU G
b0000 H
0I
UJ
bZZZZ K
b00000001100000000 L
b0000 M
0N
UO
1P
bUUUU Q
bZZZZ R
bZZZZ S
0T
0U
0V
bZZZZ W
bUUUUUUUU X
bUUUUUUUU Y
0Z
U[
0\
0]
bUUUUUUUU ^
bZZZZZZZZ _
bZZZZZZZZ `
bZZZZZZZZ a
0b
Uc
0d
0e
bUUUUUUUU f
bUUUUUUUU g
bZZZZZZZZ h
bZZZZZZZZ i
0j
Uk
0l
0m
bUUUUUUUU n
bUUUUUUUU o
bZZZZZZZZ p
bZZZZZZZZ q
0r
Us
0t
0u
bUUUUUUUU v
bZZZZZZZZ w
bZZZZZZZZ x
bZZZZZZZZ y
0z
0{
bZZZZZZZZ |
bZZZZZZZZ }
Z!"
0""
bUUUUUUUU #"
bXXXXXXXXX $"
#25000000
1!
0"
1%
1(
bZZZZZZZZ *
1+
0,
bUUUU 0
b00000100001000010 1
02
13
15
1A
1C
0D
bZZZZ F
bZZZZ G
1I
b00000100001000010 L
b0001 M
1N
0P
bZZZZ Q
bUUUU R
bUUUU S
1T
1V
bUUUU W
bZZZZZZZZ X
bZZZZZZZZ Y
1Z
1]
bZZZZZZZZ ^
1b
bZZZZZZZZ f
bZZZZZZZZ g
1j
bZZZZZZZZ n
bZZZZZZZZ o
1r
bZZZZZZZZ v
bZZZZZZZZ #"
#50000000
0!
1"
0%
0(
0A
0I
0N
0T
0Z
0b
0j
0r
#75000000
1!
0"
1%
1(
b00001110 *
1A
b1110 F
b1110 G
b0001 H
1I
b0010 M
1N
b1110 Q
1T
b00001110 X
b00001110 Y
1Z
b00001110 ^
1b
b00001110 f
b00001110 g
1j
b00001110 n
b00001110 o
1r
b00001110 v
b00001110 #"
#100000000
0!
1"
0%
0(
0A
0I
0N
0T
0Z
0b
0j
0r
#125000000
1!
0"
1%
1(
0+
b0000 .
b00001110 /
b00000000100000001 1
12
03
05
16
1A
0C
b1110 G
b0010 H
1I
b0000 K
b00000000100000001 L
b0011 M
1N
1P
1T
0V
b00001110 Y
1Z
1\
0]
b00001110 _
b00001110 `
b00001110 a
1b
b00001110 g
1j
b00001110 o
1r
b00001110 #"
#150000000
0!
1"
0%
0(
0A
0I
0N
0T
0Z
0b
0j
0r
#175000000
1!
0"
1%
1(
bZZZZZZZZ *
b1110 0
b00000000001100000 1
02
13
06
1:
1A
bZZZZ F
bZZZZ G
1I
b00000000001100000 L
b0100 M
1N
0P
bZZZZ Q
b1110 R
b1110 S
1T
1V
b1110 W
bZZZZZZZZ X
bZZZZZZZZ Y
1Z
0\
bZZZZZZZZ ^
bZZZZZZZZ _
1b
1e
bZZZZZZZZ f
bZZZZZZZZ g
1j
bZZZZZZZZ n
bZZZZZZZZ o
1r
bZZZZZZZZ v
bZZZZZZZZ #"
#200000000
0!
1"
0%
0(
0A
0I
0N
0T
0Z
0b
0j
0r
#225000000
1!
0"
1%
1(
b00000000 *
b00000000000000000 1
03
0:
1A
b0000 F
b0000 G
1I
b00000000000000000 L
b0101 M
1N
b0000 Q
1T
0V
b00000000 X
b00000000 Y
1Z
b00000000 ^
1b
0e
b00000000 f
b00000000 g
1j
b00000000 n
b00000000 o
1r
b00000000 v
b00000000 #"
#250000000
0!
1"
0%
0(
0A
0I
0N
0T
0Z
0b
0j
0r
#275000000
1!
0"
1%
1(
bZZZZZZZZ *
1A
bZZZZ F
bZZZZ G
1I
b0110 M
1N
bZZZZ Q
1T
bZZZZZZZZ X
bZZZZZZZZ Y
1Z
bZZZZZZZZ ^
1b
bZZZZZZZZ f
bZZZZZZZZ g
1j
bZZZZZZZZ n
bZZZZZZZZ o
1r
bZZZZZZZZ v
bZZZZZZZZ #"
#300000000
0!
1"
0%
0(
0A
0I
0N
0T
0Z
0b
0j
0r
#325000000
1!
0"
1%
1(
1A
bZZZZ G
1I
b0111 M
1N
1T
bZZZZZZZZ Y
1Z
1b
bZZZZZZZZ g
1j
bZZZZZZZZ o
1r
bZZZZZZZZ #"
#350000000
0!
1"
0%
0(
0A
0I
0N
0T
0Z
0b
0j
0r
#375000000
1!
0"
1%
1(
1A
bZZZZ G
1I
b1000 M
1N
1T
bZZZZZZZZ Y
1Z
1b
bZZZZZZZZ g
1j
bZZZZZZZZ o
1r
bZZZZZZZZ #"
#400000000
0!
1"
0%
0(
0A
0I
0N
0T
0Z
0b
0j
0r
#425000000
1!
0"
1%
1(
1A
bZZZZ G
1I
b1001 M
1N
1T
bZZZZZZZZ Y
1Z
1b
bZZZZZZZZ g
1j
bZZZZZZZZ o
1r
bZZZZZZZZ #"
#450000000
0!
1"
0%
0(
0A
0I
0N
0T
0Z
0b
0j
0r
#475000000
1!
0"
1%
1(
1A
bZZZZ G
1I
b1010 M
1N
1T
bZZZZZZZZ Y
1Z
1b
bZZZZZZZZ g
1j
bZZZZZZZZ o
1r
bZZZZZZZZ #"
#500000000
0!
1"
0%
0(
0A
0I
0N
0T
0Z
0b
0j
0r
#525000000
1!
0"
1%
1(
bZZZZ0010 *
1,
b00000001100000000 1
12
1A
1D
b0010 F
b0010 G
1I
b00000001100000000 L
b0000 M
1N
1P
b0010 Q
1T
bZZZZ0010 X
bZZZZ0010 Y
1Z
bZZZZ0010 ^
1b
bZZZZ0010 f
bZZZZ0010 g
1j
bZZZZ0010 n
bZZZZ0010 o
1r
bZZZZ0010 v
bZZZZ0010 #"
#550000000
0!
1"
0%
0(
0A
0I
0N
0T
0Z
0b
0j
0r
#575000000
1!
0"
1%
1(
bZZZZZZZZ *
1+
0,
b0010 0
b00000100001000010 1
02
13
15
1A
1C
0D
bZZZZ F
bZZZZ G
1I
b00000100001000010 L
b0001 M
1N
0P
bZZZZ Q
b0010 R
b0010 S
1T
1V
b0010 W
bZZZZZZZZ X
bZZZZZZZZ Y
1Z
1]
bZZZZZZZZ ^
1b
bZZZZZZZZ f
bZZZZZZZZ g
1j
bZZZZZZZZ n
bZZZZZZZZ o
1r
bZZZZZZZZ v
bZZZZZZZZ #"
#600000000
0!
1"
0%
0(
0A
0I
0N
0T
0Z
0b
0j
0r
#625000000
1!
0"
1%
1(
b00011110 *
0+
bZZZZ .
bZZZZZZZZ /
b00000000000000001 1
03
05
16
1A
0C
b1110 F
b1110 G
b0011 H
1I
bZZZZ K
b00000000000000001 L
b0010 M
1N
b1110 Q
1T
0V
b00011110 X
b00011110 Y
1Z
1\
0]
b00011110 ^
bZZZZZZZZ `
bZZZZZZZZ a
1b
b00011110 f
b00011110 g
1j
b00011110 n
b00011110 o
1r
b00011110 v
b00011110 #"
#650000000
0!
1"
0%
0(
0A
0I
0N
0T
0Z
0b
0j
0r
#675000000
1!
0"
1%
1(
bZZZZZZZZ *
1A
bZZZZ F
bZZZZ G
1I
b0011 M
1N
bZZZZ Q
1T
bZZZZZZZZ X
bZZZZZZZZ Y
1Z
bZZZZZZZZ ^
1b
bZZZZZZZZ f
bZZZZZZZZ g
1j
bZZZZZZZZ n
bZZZZZZZZ o
1r
bZZZZZZZZ v
bZZZZZZZZ #"
#700000000
0!
1"
1#
0%
1&
0(
bZZZZ0000 *
1,
bZZZZ 0
b00000001100000000 1
12
06
0A
1B
1D
b0000 F
b0000 G
b0000 H
0I
1J
b00000001100000000 L
b0000 M
0N
1O
1P
b0000 Q
bZZZZ R
bZZZZ S
0T
bZZZZ W
bZZZZ0000 X
bZZZZ0000 Y
0Z
1[
0\
bZZZZ0000 ^
0b
1c
bZZZZ0000 f
bZZZZ0000 g
0j
1k
bZZZZ0000 n
bZZZZ0000 o
0r
1s
bZZZZ0000 v
bZZZZ0000 #"
#725000000
1!
0"
1%
1(
1A
b0000 G
1I
1N
1T
bZZZZ0000 Y
1Z
1b
bZZZZ0000 g
1j
bZZZZ0000 o
1r
bZZZZ0000 #"
#750000000
0!
1"
0%
0(
0A
0I
0N
0T
0Z
0b
0j
0r
#775000000
1!
0"
1%
1(
1A
b0000 G
1I
1N
1T
bZZZZ0000 Y
1Z
1b
bZZZZ0000 g
1j
bZZZZ0000 o
1r
bZZZZ0000 #"
#800000000
0!
1"
0%
0(
0A
0I
0N
0T
0Z
0b
0j
0r
#825000000
1!
0"
1%
1(
1A
b0000 G
1I
1N
1T
bZZZZ0000 Y
1Z
1b
bZZZZ0000 g
1j
bZZZZ0000 o
1r
bZZZZ0000 #"
#850000000
0!
1"
0%
0(
0A
0I
0N
0T
0Z
0b
0j
0r
#875000000
1!
0"
1%
1(
1A
b0000 G
1I
1N
1T
bZZZZ0000 Y
1Z
1b
bZZZZ0000 g
1j
bZZZZ0000 o
1r
bZZZZ0000 #"
#900000000
0!
1"
0%
0(
0A
0I
0N
0T
0Z
0b
0j
0r
#925000000
1!
0"
1%
1(
1A
b0000 G
1I
1N
1T
bZZZZ0000 Y
1Z
1b
bZZZZ0000 g
1j
bZZZZ0000 o
1r
bZZZZ0000 #"
#950000000
0!
1"
0%
0(
0A
0I
0N
0T
0Z
0b
0j
0r
#975000000
1!
0"
1%
1(
1A
b0000 G
1I
1N
1T
bZZZZ0000 Y
1Z
1b
bZZZZ0000 g
1j
bZZZZ0000 o
1r
bZZZZ0000 #"
#1000000000
0!
1"
0%
0(
0A
0I
0N
0T
0Z
0b
0j
0r
#1025000000
1!
0"
1%
1(
1A
b0000 G
1I
1N
1T
bZZZZ0000 Y
1Z
1b
bZZZZ0000 g
1j
bZZZZ0000 o
1r
bZZZZ0000 #"
#1050000000
0!
1"
0%
0(
0A
0I
0N
0T
0Z
0b
0j
0r
#1075000000
1!
0"
1%
1(
1A
b0000 G
1I
1N
1T
bZZZZ0000 Y
1Z
1b
bZZZZ0000 g
1j
bZZZZ0000 o
1r
bZZZZ0000 #"
#1100000000
0!
1"
0%
0(
0A
0I
0N
0T
0Z
0b
0j
0r
#1125000000
1!
0"
1%
1(
1A
b0000 G
1I
1N
1T
bZZZZ0000 Y
1Z
1b
bZZZZ0000 g
1j
bZZZZ0000 o
1r
bZZZZ0000 #"
#1150000000
0!
1"
0%
0(
0A
0I
0N
0T
0Z
0b
0j
0r
#1175000000
1!
0"
1%
1(
1A
b0000 G
1I
1N
1T
bZZZZ0000 Y
1Z
1b
bZZZZ0000 g
1j
bZZZZ0000 o
1r
bZZZZ0000 #"
#1200000000
0!
1"
0#
0%
0&
0(
0A
0B
0I
0J
0N
0O
0T
0Z
0[
0b
0c
0j
0k
0r
0s
#1225000000
1!
0"
1%
1(
bZZZZZZZZ *
1+
0,
b0000 0
b00000100001000010 1
02
13
15
1A
1C
0D
bZZZZ F
bZZZZ G
1I
b00000100001000010 L
b0001 M
1N
0P
bZZZZ Q
b0000 R
b0000 S
1T
1V
b0000 W
bZZZZZZZZ X
bZZZZZZZZ Y
1Z
1]
bZZZZZZZZ ^
1b
bZZZZZZZZ f
bZZZZZZZZ g
1j
bZZZZZZZZ n
bZZZZZZZZ o
1r
bZZZZZZZZ v
bZZZZZZZZ #"
#1250000000
0!
1"
0%
0(
0A
0I
0N
0T
0Z
0b
0j
0r
#1275000000
1!
0"
1%
1(
b00001110 *
1A
b1110 F
b1110 G
b0001 H
1I
b0010 M
1N
b1110 Q
1T
b00001110 X
b00001110 Y
1Z
b00001110 ^
1b
b00001110 f
b00001110 g
1j
b00001110 n
b00001110 o
1r
b00001110 v
b00001110 #"
#1300000000
0!
1"
0%
0(
0A
0I
0N
0T
0Z
0b
0j
0r
